Metadata-Version: 1.0
Name: calman
Version: 0.0.1
Summary: Stay calm with kalman filters
Home-page: https://github.com/tsitsimis/calman
Author: Theodore tsitsimis
Author-email: thodotsi@gmail.com
License: MIT
Platform: UNKNOWN
